examples/__init__.py
examples/run_as_function.py
examples/run_as_implement.py
examples/test_files/__init__.py
tests/__init__.py
tests/test_config.py
tests/test_function.py
tests/test_implement.py
tinyCrawl/__init__.py
tinyCrawl/base/__init__.py
tinyCrawl/base/base.py
tinyCrawl/base/base_container.py
tinyCrawl/common/__init__.py
tinyCrawl/common/config.py
tinyCrawl/utils/__init__.py
tinyCrawl/utils/logger.py
tinyCrawl/utils/utils.py
tinyCrawl-0.1.2.dist-info/LICENSE
tinyCrawl-0.1.2.dist-info/METADATA
tinyCrawl-0.1.2.dist-info/WHEEL
tinyCrawl-0.1.2.dist-info/top_level.txt
tinyCrawl-0.1.2.dist-info/RECORD
