Metadata-Version: 2.1
Name: tinyCrawl
Version: 0.1.2
Summary: Very easy and tiny crawling framework, support multithread processing.
Home-page: https://github.com/Irvinfaith/tinyCrawl
Author: Irvinfaith
Author-email: waxiguan00@hotmail.com
License: MIT
Platform: python 3.6
Classifier: Programming Language :: Python :: 3
Classifier: Programming Language :: Python :: 3.6
Classifier: Programming Language :: Python :: 3.7
Classifier: Programming Language :: Python :: 3.8
Classifier: Programming Language :: Python :: 3.9
Classifier: Operating System :: OS Independent
Requires-Python: >=3.6,<4
